update_workflows.py
update_workflows-0.2.dist-info/licenses/LICENSE
update_workflows-0.2.dist-info/METADATA
update_workflows-0.2.dist-info/WHEEL
update_workflows-0.2.dist-info/entry_points.txt
update_workflows-0.2.dist-info/top_level.txt
update_workflows-0.2.dist-info/RECORD
