Metadata-Version: 2.4
Name: update-workflows
Version: 0.2
Summary: Update GitHub Actions Workflows
Author: Simon Willison
License-Expression: Apache-2.0
Project-URL: Homepage, https://github.com/simonw/update-workflows
Project-URL: Changelog, https://github.com/simonw/update-workflows/releases
Project-URL: Issues, https://github.com/simonw/update-workflows/issues
Project-URL: CI, https://github.com/simonw/update-workflows/actions
Classifier: Intended Audience :: Developers
Classifier: Topic :: Software Development :: Build Tools
Requires-Python: >=3.10
License-File: LICENSE
Requires-Dist: PyYAML>=6.0
Provides-Extra: test
Requires-Dist: pytest>=7.0.0; extra == "test"
Requires-Dist: pytest-cov>=4.0.0; extra == "test"
Dynamic: license-file
